requests_skip_verify/__init__.py
requests_skip_verify/main.py
requests_skip_verify-0.0.2.dist-info/LICENSE
requests_skip_verify-0.0.2.dist-info/METADATA
requests_skip_verify-0.0.2.dist-info/WHEEL
requests_skip_verify-0.0.2.dist-info/top_level.txt
requests_skip_verify-0.0.2.dist-info/RECORD
