Metadata-Version: 2.1
Name: requests-skip-verify
Version: 0.0.2
Summary: Skip SSL verification for requests.
Home-page: UNKNOWN
Author: Tsuuko
License: MIT
Platform: UNKNOWN
Classifier: Programming Language :: Python :: 3
Classifier: License :: OSI Approved :: MIT License
Classifier: Operating System :: OS Independent
